efc/__init__.py
efc/settings.py
efc/utils.py
efc/base/__init__.py
efc/base/errors.py
efc/interfaces/__init__.py
efc/interfaces/base.py
efc/interfaces/cache.py
efc/interfaces/errors.py
efc/interfaces/iopenpyxl.py
efc/rpn_builder/__init__.py
efc/rpn_builder/errors.py
efc/rpn_builder/rpn.py
efc/rpn_builder/lexer/__init__.py
efc/rpn_builder/lexer/errors.py
efc/rpn_builder/lexer/lexer.py
efc/rpn_builder/lexer/tokens.py
efc/rpn_builder/parser/__init__.py
efc/rpn_builder/parser/errors.py
efc/rpn_builder/parser/functions.py
efc/rpn_builder/parser/metaclasses.py
efc/rpn_builder/parser/operands.py
efc/rpn_builder/parser/operations.py
efc/rpn_builder/parser/parser.py
tests/__init__.py
tests/test_utils.py
tests/test_interfaces/__init__.py
tests/test_interfaces/test_iopenpyxl.py
tests/test_lexer/__init__.py
tests/test_lexer/test_errors.py
tests/test_lexer/test_lexer.py
tests/test_lexer/test_tokens.py
tests/test_parser/__init__.py
tests/test_parser/test_parser.py
tests/test_rpn/__init__.py
tests/test_rpn/mock.py
tests/test_rpn/test_arith.py
tests/test_rpn/test_cells.py
tests/test_rpn/test_common.py
tests/test_rpn/test_functions.py
excel_formulas_calculator-0.5.0.dist-info/LICENSE
excel_formulas_calculator-0.5.0.dist-info/METADATA
excel_formulas_calculator-0.5.0.dist-info/WHEEL
excel_formulas_calculator-0.5.0.dist-info/top_level.txt
excel_formulas_calculator-0.5.0.dist-info/RECORD
