Metadata-Version: 2.1
Name: excel-formulas-calculator
Version: 0.5.0
Summary: Library to calculate excel formulas
Home-page: https://github.com/ulalka/excel-formulas-calculator
Author: Gleb Orlov
Author-email: orlovgb@mail.ru
License: MIT
Classifier: Development Status :: 2 - Pre-Alpha
Classifier: Programming Language :: Python :: 2
Classifier: Programming Language :: Python :: 3
Classifier: Intended Audience :: Developers
Classifier: License :: OSI Approved :: MIT License
Requires-Python: >=2.7, !=3.0.*, !=3.1.*, !=3.2.*, !=3.3.*, !=3.4.*, !=3.5.*, <4
License-File: LICENSE
Requires-Dist: six
Provides-Extra: openpyxl-py2
Requires-Dist: openpyxl >=2.6.4 ; extra == 'openpyxl-py2'
Provides-Extra: openpyxl-py3
Requires-Dist: openpyxl >=3.1.2 ; extra == 'openpyxl-py3'
